quote_module/__init__.py
quote_module/libquote_module.so
quote_module/pcap_file_offline_reader.c
quote_module/quote_module.py
quote_module/quote_parser.c
quote_module/test.py
quote_module/utils.c
quote_module/utils.h
quote_module-0.0.23.dist-info/METADATA
quote_module-0.0.23.dist-info/WHEEL
quote_module-0.0.23.dist-info/top_level.txt
quote_module-0.0.23.dist-info/RECORD
