Metadata-Version: 2.4
Name: quote_module
Version: 0.0.23
Summary: Your package description
Home-page: https://github.com/williamchen180/quote_module
Author: William Chen
Author-email: williamchen180@gmail.com
Platform: linux_x86_64
Classifier: Programming Language :: Python :: 3
Classifier: License :: OSI Approved :: MIT License
Classifier: Operating System :: OS Independent
Requires-Dist: setuptools
Requires-Dist: wheel
Requires-Dist: twine
Dynamic: author
Dynamic: author-email
Dynamic: classifier
Dynamic: description
Dynamic: description-content-type
Dynamic: home-page
Dynamic: platform
Dynamic: requires-dist
Dynamic: summary
